cornac/__init__.py
cornac/__main__.py
cornac/cli.py
cornac/core/__init__.py
cornac/core/config/__init__.py
cornac/core/config/defaults.py
cornac/core/config/writer.py
cornac/core/instanceclass.py
cornac/core/model.py
cornac/core/orm.py
cornac/core/schema/000-init.sql
cornac/core/schema/001-instances.sql
cornac/core/schema/002-dramatiq.sql
cornac/core/schema/003-snapshots.sql
cornac/core/schema/004-accounts.sql
cornac/core/schema/005-virtual-ip.sql
cornac/core/schema/__init__.py
cornac/core/schema/migrator.py
cornac/core/user.py
cornac/errors.py
cornac/etcd.py
cornac/files/bashrc
cornac/files/cornac-scheduler.service
cornac/files/cornac-script
cornac/files/cornac-setup
cornac/files/cornac-shell
cornac/files/cornac-web.service
cornac/files/cornac-worker@.service
cornac/files/createdb
cornac/files/haping
cornac/files/pqenv
cornac/files/purge.sh
cornac/files/ssh_config
cornac/files/switchaccount
cornac/iaas/__init__.py
cornac/iaas/libvirt.py
cornac/iaas/none.py
cornac/iaas/vcenter.py
cornac/iaas/vhelper.sh
cornac/operator/__init__.py
cornac/operator/base.py
cornac/operator/basic.py
cornac/operator/machine.py
cornac/operator/none.py
cornac/operator/pghelper.sh
cornac/ssh.py
cornac/temboard.py
cornac/utils.py
cornac/web/__init__.py
cornac/web/auth.py
cornac/web/cornac/__init__.py
cornac/web/cornac/accounts.py
cornac/web/cornac/auth.py
cornac/web/cornac/blueprint.py
cornac/web/cornac/cloudinit.py
cornac/web/cornac/rds.py
cornac/web/cornac/root.py
cornac/web/cornac/temboard.py
cornac/web/endpoint.py
cornac/web/errors.py
cornac/web/iam/__init__.py
cornac/web/iam/actions.py
cornac/web/iam/errors.py
cornac/web/iam/xml.py
cornac/web/rds/__init__.py
cornac/web/rds/actions.py
cornac/web/rds/errors.py
cornac/web/rds/xml.py
cornac/web/sts/__init__.py
cornac/web/sts/actions.py
cornac/web/sts/xml.py
cornac/web/utils.py
cornac/web/xml.py
cornac/worker.py
pgcornac-2.0.0.dist-info/entry_points.txt
pgcornac-2.0.0.dist-info/WHEEL
pgcornac-2.0.0.dist-info/METADATA
pgcornac-2.0.0.dist-info/RECORD
